[
  {
    "板块": "Energy",
    "平均涨跌幅": 7.245722222222223,
    "股票数量": 180
  },
  {
    "板块": "Communications",
    "平均涨跌幅": 3.927142857142857,
    "股票数量": 42
  },
  {
    "板块": "Industrial Conglomerates",
    "平均涨跌幅": 3.2075,
    "股票数量": 4
  },
  {
    "板块": "Aerospace & Defense",
    "平均涨跌幅": 2.790597014925373,
    "股票数量": 67
  },
  {
    "板块": "Marine",
    "平均涨跌幅": 2.661,
    "股票数量": 30
  },
  {
    "板块": "Metals & Mining",
    "平均涨跌幅": 2.2219178082191777,
    "股票数量": 73
  },
  {
    "板块": "Semiconductors",
    "平均涨跌幅": 2.214468085106383,
    "股票数量": 94
  },
  {
    "板块": "Road & Rail",
    "平均涨跌幅": 2.0611111111111113,
    "股票数量": 36
  },
  {
    "板块": "Telecommunication",
    "平均涨跌幅": 1.5291428571428571,
    "股票数量": 35
  },
  {
    "板块": "Electrical Equipment",
    "平均涨跌幅": 1.4435754189944132,
    "股票数量": 179
  },
  {
    "板块": "Banking",
    "平均涨跌幅": 1.2369741697416974,
    "股票数量": 271
  },
  {
    "板块": "Insurance",
    "平均涨跌幅": 1.2220388349514564,
    "股票数量": 103
  },
  {
    "板块": "Logistics & Transportation",
    "平均涨跌幅": 1.1425,
    "股票数量": 16
  },
  {
    "板块": "Financial Services",
    "平均涨跌幅": 1.0549070631970259,
    "股票数量": 269
  },
  {
    "板块": "Technology",
    "平均涨跌幅": 0.9794212218649518,
    "股票数量": 311
  },
  {
    "板块": "Transportation Infrastructure",
    "平均涨跌幅": 0.84,
    "股票数量": 3
  },
  {
    "板块": "Professional Services",
    "平均涨跌幅": 0.4196551724137931,
    "股票数量": 87
  },
  {
    "板块": "Utilities",
    "平均涨跌幅": 0.35803030303030303,
    "股票数量": 66
  },
  {
    "板块": "Trading Companies & Distributors",
    "平均涨跌幅": 0.3333333333333333,
    "股票数量": 36
  },
  {
    "板块": "Machinery",
    "平均涨跌幅": 0.31009009009009003,
    "股票数量": 111
  },
  {
    "板块": "Construction",
    "平均涨跌幅": 0.1781481481481481,
    "股票数量": 54
  },
  {
    "板块": "Distributors",
    "平均涨跌幅": 0.045500000000000186,
    "股票数量": 20
  },
  {
    "板块": "N/A",
    "平均涨跌幅": -0.08496688741721856,
    "股票数量": 151
  },
  {
    "板块": "Biotechnology",
    "平均涨跌幅": -0.21949671772428886,
    "股票数量": 457
  },
  {
    "板块": "Chemicals",
    "平均涨跌幅": -0.2598507462686567,
    "股票数量": 67
  },
  {
    "板块": "Building",
    "平均涨跌幅": -0.2727272727272727,
    "股票数量": 33
  },
  {
    "板块": "Auto Components",
    "平均涨跌幅": -0.35742857142857143,
    "股票数量": 35
  },
  {
    "板块": "Health Care",
    "平均涨跌幅": -0.4016107382550335,
    "股票数量": 298
  },
  {
    "板块": "Media",
    "平均涨跌幅": -0.47390374331550805,
    "股票数量": 187
  },
  {
    "板块": "Automobiles",
    "平均涨跌幅": -0.54,
    "股票数量": 25
  },
  {
    "板块": "Pharmaceuticals",
    "平均涨跌幅": -0.592360248447205,
    "股票数量": 161
  },
  {
    "板块": "Commercial Services & Supplies",
    "平均涨跌幅": -0.6469565217391304,
    "股票数量": 69
  },
  {
    "板块": "Hotels, Restaurants & Leisure",
    "平均涨跌幅": -0.9040186915887851,
    "股票数量": 107
  },
  {
    "板块": "Real Estate",
    "平均涨跌幅": -0.9087719298245613,
    "股票数量": 57
  },
  {
    "板块": "Food Products",
    "平均涨跌幅": -0.9772857142857142,
    "股票数量": 70
  },
  {
    "板块": "Life Sciences Tools & Services",
    "平均涨跌幅": -1.1072,
    "股票数量": 50
  },
  {
    "板块": "Beverages",
    "平均涨跌幅": -1.1800000000000002,
    "股票数量": 21
  },
  {
    "板块": "Packaging",
    "平均涨跌幅": -1.2904761904761903,
    "股票数量": 21
  },
  {
    "板块": "Retail",
    "平均涨跌幅": -1.4756737588652482,
    "股票数量": 141
  },
  {
    "板块": "Paper & Forest",
    "平均涨跌幅": -1.56,
    "股票数量": 5
  },
  {
    "板块": "Diversified Consumer Services",
    "平均涨跌幅": -1.7659183673469387,
    "股票数量": 49
  },
  {
    "板块": "Consumer products",
    "平均涨跌幅": -1.7684782608695655,
    "股票数量": 92
  },
  {
    "板块": "Airlines",
    "平均涨跌幅": -2.1023529411764703,
    "股票数量": 17
  },
  {
    "板块": "Textiles, Apparel & Luxury Goods",
    "平均涨跌幅": -2.135581395348837,
    "股票数量": 43
  },
  {
    "板块": "Leisure Products",
    "平均涨跌幅": -2.2455555555555557,
    "股票数量": 27
  },
  {
    "板块": "Tobacco",
    "平均涨跌幅": -4.916666666666667,
    "股票数量": 6
  }
]