[
  {
    "板块": "Beverages",
    "平均涨跌幅": 7.7275,
    "股票数量": 8
  },
  {
    "板块": "Transportation Infrastructure",
    "平均涨跌幅": 5.39,
    "股票数量": 1
  },
  {
    "板块": "Airlines",
    "平均涨跌幅": 5.162857142857143,
    "股票数量": 7
  },
  {
    "板块": "Electrical Equipment",
    "平均涨跌幅": 3.2011111111111106,
    "股票数量": 90
  },
  {
    "板块": "Building",
    "平均涨跌幅": 2.7725,
    "股票数量": 16
  },
  {
    "板块": "N/A",
    "平均涨跌幅": 2.58,
    "股票数量": 4
  },
  {
    "板块": "Marine",
    "平均涨跌幅": 2.3516666666666666,
    "股票数量": 12
  },
  {
    "板块": "Diversified Consumer Services",
    "平均涨跌幅": 2.24,
    "股票数量": 19
  },
  {
    "板块": "Metals & Mining",
    "平均涨跌幅": 2.239189189189189,
    "股票数量": 37
  },
  {
    "板块": "Biotechnology",
    "平均涨跌幅": 2.1607142857142856,
    "股票数量": 210
  },
  {
    "板块": "Leisure Products",
    "平均涨跌幅": 2.13,
    "股票数量": 9
  },
  {
    "板块": "Food Products",
    "平均涨跌幅": 2.01448275862069,
    "股票数量": 29
  },
  {
    "板块": "Pharmaceuticals",
    "平均涨跌幅": 2.0130666666666666,
    "股票数量": 75
  },
  {
    "板块": "Semiconductors",
    "平均涨跌幅": 1.679622641509434,
    "股票数量": 53
  },
  {
    "板块": "Retail",
    "平均涨跌幅": 1.6395714285714285,
    "股票数量": 70
  },
  {
    "板块": "Textiles, Apparel & Luxury Goods",
    "平均涨跌幅": 1.585416666666667,
    "股票数量": 24
  },
  {
    "板块": "Aerospace & Defense",
    "平均涨跌幅": 1.575357142857143,
    "股票数量": 28
  },
  {
    "板块": "Financial Services",
    "平均涨跌幅": 1.5376033057851242,
    "股票数量": 121
  },
  {
    "板块": "Communications",
    "平均涨跌幅": 1.5,
    "股票数量": 24
  },
  {
    "板块": "Construction",
    "平均涨跌幅": 1.3463999999999998,
    "股票数量": 25
  },
  {
    "板块": "Utilities",
    "平均涨跌幅": 1.328235294117647,
    "股票数量": 34
  },
  {
    "板块": "Health Care",
    "平均涨跌幅": 1.2355072463768115,
    "股票数量": 138
  },
  {
    "板块": "Media",
    "平均涨跌幅": 1.1619736842105264,
    "股票数量": 76
  },
  {
    "板块": "Tobacco",
    "平均涨跌幅": 0.9425,
    "股票数量": 4
  },
  {
    "板块": "Automobiles",
    "平均涨跌幅": 0.932,
    "股票数量": 10
  },
  {
    "板块": "Chemicals",
    "平均涨跌幅": 0.9151515151515152,
    "股票数量": 33
  },
  {
    "板块": "Consumer products",
    "平均涨跌幅": 0.7423913043478261,
    "股票数量": 46
  },
  {
    "板块": "Hotels, Restaurants & Leisure",
    "平均涨跌幅": 0.6006382978723405,
    "股票数量": 47
  },
  {
    "板块": "Professional Services",
    "平均涨跌幅": 0.5329545454545456,
    "股票数量": 44
  },
  {
    "板块": "Packaging",
    "平均涨跌幅": 0.5285714285714286,
    "股票数量": 7
  },
  {
    "板块": "Auto Components",
    "平均涨跌幅": 0.527391304347826,
    "股票数量": 23
  },
  {
    "板块": "Trading Companies & Distributors",
    "平均涨跌幅": 0.5046153846153846,
    "股票数量": 13
  },
  {
    "板块": "Commercial Services & Supplies",
    "平均涨跌幅": 0.47413793103448276,
    "股票数量": 29
  },
  {
    "板块": "Insurance",
    "平均涨跌幅": 0.43511627906976746,
    "股票数量": 43
  },
  {
    "板块": "Technology",
    "平均涨跌幅": 0.34986111111111107,
    "股票数量": 144
  },
  {
    "板块": "Real Estate",
    "平均涨跌幅": 0.3284615384615384,
    "股票数量": 26
  },
  {
    "板块": "Life Sciences Tools & Services",
    "平均涨跌幅": 0.2464,
    "股票数量": 25
  },
  {
    "板块": "Energy",
    "平均涨跌幅": 0.011315789473684203,
    "股票数量": 76
  },
  {
    "板块": "Logistics & Transportation",
    "平均涨跌幅": -0.09142857142857126,
    "股票数量": 7
  },
  {
    "板块": "Distributors",
    "平均涨跌幅": -0.2014285714285715,
    "股票数量": 7
  },
  {
    "板块": "Banking",
    "平均涨跌幅": -0.22264957264957266,
    "股票数量": 117
  },
  {
    "板块": "Paper & Forest",
    "平均涨跌幅": -0.35,
    "股票数量": 1
  },
  {
    "板块": "Industrial Conglomerates",
    "平均涨跌幅": -0.485,
    "股票数量": 2
  },
  {
    "板块": "Machinery",
    "平均涨跌幅": -0.5936842105263158,
    "股票数量": 57
  },
  {
    "板块": "Telecommunication",
    "平均涨跌幅": -0.8889999999999999,
    "股票数量": 10
  },
  {
    "板块": "Road & Rail",
    "平均涨跌幅": -2.1389473684210527,
    "股票数量": 19
  }
]