[
  {
    "板块": "Professional Services",
    "平均涨跌幅": 2.0298850574712644,
    "股票数量": 87
  },
  {
    "板块": "Transportation Infrastructure",
    "平均涨跌幅": 1.6366666666666667,
    "股票数量": 3
  },
  {
    "板块": "Real Estate",
    "平均涨跌幅": 1.2651785714285713,
    "股票数量": 56
  },
  {
    "板块": "Tobacco",
    "平均涨跌幅": 1.0883333333333332,
    "股票数量": 6
  },
  {
    "板块": "Insurance",
    "平均涨跌幅": 0.8764705882352942,
    "股票数量": 102
  },
  {
    "板块": "Banking",
    "平均涨跌幅": 0.8427799227799228,
    "股票数量": 259
  },
  {
    "板块": "Trading Companies & Distributors",
    "平均涨跌幅": 0.6762162162162162,
    "股票数量": 37
  },
  {
    "板块": "Road & Rail",
    "平均涨跌幅": 0.6354054054054054,
    "股票数量": 37
  },
  {
    "板块": "Energy",
    "平均涨跌幅": 0.5074175824175824,
    "股票数量": 182
  },
  {
    "板块": "Beverages",
    "平均涨跌幅": 0.25999999999999995,
    "股票数量": 19
  },
  {
    "板块": "Leisure Products",
    "平均涨跌幅": 0.20481481481481487,
    "股票数量": 27
  },
  {
    "板块": "Financial Services",
    "平均涨跌幅": 0.1917110266159696,
    "股票数量": 263
  },
  {
    "板块": "Telecommunication",
    "平均涨跌幅": 0.06842105263157894,
    "股票数量": 38
  },
  {
    "板块": "Packaging",
    "平均涨跌幅": 0.05315789473684214,
    "股票数量": 19
  },
  {
    "板块": "Textiles, Apparel & Luxury Goods",
    "平均涨跌幅": -0.1384090909090909,
    "股票数量": 44
  },
  {
    "板块": "Consumer products",
    "平均涨跌幅": -0.17510638297872338,
    "股票数量": 94
  },
  {
    "板块": "Automobiles",
    "平均涨跌幅": -0.22818181818181812,
    "股票数量": 22
  },
  {
    "板块": "Media",
    "平均涨跌幅": -0.24796875,
    "股票数量": 192
  },
  {
    "板块": "N/A",
    "平均涨跌幅": -0.28211538461538466,
    "股票数量": 156
  },
  {
    "板块": "Health Care",
    "平均涨跌幅": -0.3315666666666667,
    "股票数量": 300
  },
  {
    "板块": "Food Products",
    "平均涨跌幅": -0.35478873239436615,
    "股票数量": 71
  },
  {
    "板块": "Hotels, Restaurants & Leisure",
    "平均涨跌幅": -0.3812037037037037,
    "股票数量": 108
  },
  {
    "板块": "Retail",
    "平均涨跌幅": -0.5883571428571429,
    "股票数量": 140
  },
  {
    "板块": "Utilities",
    "平均涨跌幅": -0.6073134328358208,
    "股票数量": 67
  },
  {
    "板块": "Airlines",
    "平均涨跌幅": -0.7523529411764706,
    "股票数量": 17
  },
  {
    "板块": "Paper & Forest",
    "平均涨跌幅": -0.8219999999999998,
    "股票数量": 5
  },
  {
    "板块": "Diversified Consumer Services",
    "平均涨跌幅": -0.863125,
    "股票数量": 48
  },
  {
    "板块": "Life Sciences Tools & Services",
    "平均涨跌幅": -0.8663461538461538,
    "股票数量": 52
  },
  {
    "板块": "Construction",
    "平均涨跌幅": -0.8764912280701753,
    "股票数量": 57
  },
  {
    "板块": "Technology",
    "平均涨跌幅": -0.9888888888888889,
    "股票数量": 306
  },
  {
    "板块": "Chemicals",
    "平均涨跌幅": -1.0965671641791044,
    "股票数量": 67
  },
  {
    "板块": "Industrial Conglomerates",
    "平均涨跌幅": -1.11,
    "股票数量": 4
  },
  {
    "板块": "Distributors",
    "平均涨跌幅": -1.1404761904761904,
    "股票数量": 21
  },
  {
    "板块": "Pharmaceuticals",
    "平均涨跌幅": -1.377037037037037,
    "股票数量": 162
  },
  {
    "板块": "Machinery",
    "平均涨跌幅": -1.3910714285714287,
    "股票数量": 112
  },
  {
    "板块": "Auto Components",
    "平均涨跌幅": -1.4313888888888888,
    "股票数量": 36
  },
  {
    "板块": "Biotechnology",
    "平均涨跌幅": -1.438008849557522,
    "股票数量": 452
  },
  {
    "板块": "Building",
    "平均涨跌幅": -1.47625,
    "股票数量": 32
  },
  {
    "板块": "Electrical Equipment",
    "平均涨跌幅": -1.5480769230769231,
    "股票数量": 182
  },
  {
    "板块": "Logistics & Transportation",
    "平均涨跌幅": -1.7511764705882356,
    "股票数量": 17
  },
  {
    "板块": "Aerospace & Defense",
    "平均涨跌幅": -1.7598461538461538,
    "股票数量": 65
  },
  {
    "板块": "Commercial Services & Supplies",
    "平均涨跌幅": -1.913913043478261,
    "股票数量": 69
  },
  {
    "板块": "Marine",
    "平均涨跌幅": -2.862,
    "股票数量": 30
  },
  {
    "板块": "Metals & Mining",
    "平均涨跌幅": -3.012,
    "股票数量": 75
  },
  {
    "板块": "Communications",
    "平均涨跌幅": -3.548780487804878,
    "股票数量": 41
  },
  {
    "板块": "Semiconductors",
    "平均涨跌幅": -4.450833333333333,
    "股票数量": 96
  }
]