[
  {
    "板块": "Airlines",
    "平均涨跌幅": 3.92875,
    "股票数量": 8
  },
  {
    "板块": "Life Sciences Tools & Services",
    "平均涨跌幅": 3.39,
    "股票数量": 30
  },
  {
    "板块": "Marine",
    "平均涨跌幅": 2.208,
    "股票数量": 15
  },
  {
    "板块": "Road & Rail",
    "平均涨跌幅": 1.7654545454545456,
    "股票数量": 22
  },
  {
    "板块": "Packaging",
    "平均涨跌幅": 1.437,
    "股票数量": 10
  },
  {
    "板块": "Technology",
    "平均涨跌幅": 1.3241714285714286,
    "股票数量": 175
  },
  {
    "板块": "Pharmaceuticals",
    "平均涨跌幅": 1.2780681818181818,
    "股票数量": 88
  },
  {
    "板块": "Paper & Forest",
    "平均涨跌幅": 1.2700000000000002,
    "股票数量": 3
  },
  {
    "板块": "Telecommunication",
    "平均涨跌幅": 1.261764705882353,
    "股票数量": 17
  },
  {
    "板块": "Biotechnology",
    "平均涨跌幅": 1.2186746987951806,
    "股票数量": 249
  },
  {
    "板块": "Automobiles",
    "平均涨跌幅": 1.2041666666666666,
    "股票数量": 12
  },
  {
    "板块": "Aerospace & Defense",
    "平均涨跌幅": 1.1884848484848485,
    "股票数量": 33
  },
  {
    "板块": "Real Estate",
    "平均涨跌幅": 1.1644444444444444,
    "股票数量": 27
  },
  {
    "板块": "Media",
    "平均涨跌幅": 1.140744680851064,
    "股票数量": 94
  },
  {
    "板块": "Semiconductors",
    "平均涨跌幅": 1.066451612903226,
    "股票数量": 62
  },
  {
    "板块": "Electrical Equipment",
    "平均涨跌幅": 1.046574074074074,
    "股票数量": 108
  },
  {
    "板块": "Financial Services",
    "平均涨跌幅": 0.9380689655172415,
    "股票数量": 145
  },
  {
    "板块": "Construction",
    "平均涨跌幅": 0.7373333333333333,
    "股票数量": 30
  },
  {
    "板块": "Insurance",
    "平均涨跌幅": 0.5655102040816327,
    "股票数量": 49
  },
  {
    "板块": "N/A",
    "平均涨跌幅": 0.502,
    "股票数量": 5
  },
  {
    "板块": "Chemicals",
    "平均涨跌幅": 0.47621621621621624,
    "股票数量": 37
  },
  {
    "板块": "Logistics & Transportation",
    "平均涨跌幅": 0.395,
    "股票数量": 8
  },
  {
    "板块": "Industrial Conglomerates",
    "平均涨跌幅": 0.32,
    "股票数量": 2
  },
  {
    "板块": "Hotels, Restaurants & Leisure",
    "平均涨跌幅": 0.3127118644067797,
    "股票数量": 59
  },
  {
    "板块": "Auto Components",
    "平均涨跌幅": 0.16038461538461546,
    "股票数量": 26
  },
  {
    "板块": "Professional Services",
    "平均涨跌幅": 0.14326923076923082,
    "股票数量": 52
  },
  {
    "板块": "Machinery",
    "平均涨跌幅": 0.11420289855072466,
    "股票数量": 69
  },
  {
    "板块": "Consumer products",
    "平均涨跌幅": 0.08241379310344826,
    "股票数量": 58
  },
  {
    "板块": "Beverages",
    "平均涨跌幅": 0.020000000000000018,
    "股票数量": 9
  },
  {
    "板块": "Metals & Mining",
    "平均涨跌幅": -0.06046511627906976,
    "股票数量": 43
  },
  {
    "板块": "Communications",
    "平均涨跌幅": -0.08357142857142853,
    "股票数量": 28
  },
  {
    "板块": "Energy",
    "平均涨跌幅": -0.12819148936170213,
    "股票数量": 94
  },
  {
    "板块": "Building",
    "平均涨跌幅": -0.1375,
    "股票数量": 20
  },
  {
    "板块": "Textiles, Apparel & Luxury Goods",
    "平均涨跌幅": -0.26185185185185184,
    "股票数量": 27
  },
  {
    "板块": "Transportation Infrastructure",
    "平均涨跌幅": -0.32,
    "股票数量": 1
  },
  {
    "板块": "Banking",
    "平均涨跌幅": -0.3215646258503402,
    "股票数量": 147
  },
  {
    "板块": "Trading Companies & Distributors",
    "平均涨跌幅": -0.4672222222222222,
    "股票数量": 18
  },
  {
    "板块": "Health Care",
    "平均涨跌幅": -0.521867469879518,
    "股票数量": 166
  },
  {
    "板块": "Commercial Services & Supplies",
    "平均涨跌幅": -0.6597222222222222,
    "股票数量": 36
  },
  {
    "板块": "Leisure Products",
    "平均涨跌幅": -0.735,
    "股票数量": 12
  },
  {
    "板块": "Diversified Consumer Services",
    "平均涨跌幅": -1.0124,
    "股票数量": 25
  },
  {
    "板块": "Utilities",
    "平均涨跌幅": -1.089,
    "股票数量": 40
  },
  {
    "板块": "Food Products",
    "平均涨跌幅": -1.1715,
    "股票数量": 40
  },
  {
    "板块": "Distributors",
    "平均涨跌幅": -1.4042857142857141,
    "股票数量": 7
  },
  {
    "板块": "Retail",
    "平均涨跌幅": -1.7395555555555555,
    "股票数量": 90
  },
  {
    "板块": "Tobacco",
    "平均涨跌幅": -2.325,
    "股票数量": 4
  }
]