[
  {
    "板块": "Telecommunication",
    "平均涨跌幅": 2.9469444444444446,
    "股票数量": 36
  },
  {
    "板块": "Distributors",
    "平均涨跌幅": 1.7740000000000002,
    "股票数量": 20
  },
  {
    "板块": "Marine",
    "平均涨跌幅": 1.5813333333333333,
    "股票数量": 30
  },
  {
    "板块": "Energy",
    "平均涨跌幅": 1.3567777777777779,
    "股票数量": 180
  },
  {
    "板块": "Chemicals",
    "平均涨跌幅": 0.880144927536232,
    "股票数量": 69
  },
  {
    "板块": "Communications",
    "平均涨跌幅": 0.411904761904762,
    "股票数量": 42
  },
  {
    "板块": "Packaging",
    "平均涨跌幅": -0.0605,
    "股票数量": 20
  },
  {
    "板块": "Utilities",
    "平均涨跌幅": -0.0768181818181818,
    "股票数量": 66
  },
  {
    "板块": "Food Products",
    "平均涨跌幅": -0.08811594202898548,
    "股票数量": 69
  },
  {
    "板块": "Media",
    "平均涨跌幅": -0.1414285714285714,
    "股票数量": 189
  },
  {
    "板块": "N/A",
    "平均涨跌幅": -0.1943076923076923,
    "股票数量": 130
  },
  {
    "板块": "Beverages",
    "平均涨跌幅": -0.35736842105263156,
    "股票数量": 19
  },
  {
    "板块": "Biotechnology",
    "平均涨跌幅": -0.4471553610503282,
    "股票数量": 457
  },
  {
    "板块": "Road & Rail",
    "平均涨跌幅": -0.4872222222222222,
    "股票数量": 36
  },
  {
    "板块": "Building",
    "平均涨跌幅": -0.5029411764705882,
    "股票数量": 34
  },
  {
    "板块": "Metals & Mining",
    "平均涨跌幅": -0.6249315068493151,
    "股票数量": 73
  },
  {
    "板块": "Paper & Forest",
    "平均涨跌幅": -0.734,
    "股票数量": 5
  },
  {
    "板块": "Trading Companies & Distributors",
    "平均涨跌幅": -0.9938888888888889,
    "股票数量": 36
  },
  {
    "板块": "Insurance",
    "平均涨跌幅": -0.9973267326732673,
    "股票数量": 101
  },
  {
    "板块": "Life Sciences Tools & Services",
    "平均涨跌幅": -1.0062,
    "股票数量": 50
  },
  {
    "板块": "Construction",
    "平均涨跌幅": -1.0538888888888889,
    "股票数量": 54
  },
  {
    "板块": "Consumer products",
    "平均涨跌幅": -1.2432608695652174,
    "股票数量": 92
  },
  {
    "板块": "Logistics & Transportation",
    "平均涨跌幅": -1.323125,
    "股票数量": 16
  },
  {
    "板块": "Professional Services",
    "平均涨跌幅": -1.3363218390804597,
    "股票数量": 87
  },
  {
    "板块": "Health Care",
    "平均涨跌幅": -1.3461073825503356,
    "股票数量": 298
  },
  {
    "板块": "Pharmaceuticals",
    "平均涨跌幅": -1.3903703703703705,
    "股票数量": 162
  },
  {
    "板块": "Machinery",
    "平均涨跌幅": -1.5884545454545453,
    "股票数量": 110
  },
  {
    "板块": "Commercial Services & Supplies",
    "平均涨跌幅": -1.5928358208955224,
    "股票数量": 67
  },
  {
    "板块": "Real Estate",
    "平均涨跌幅": -1.6171428571428572,
    "股票数量": 56
  },
  {
    "板块": "Textiles, Apparel & Luxury Goods",
    "平均涨跌幅": -1.624186046511628,
    "股票数量": 43
  },
  {
    "板块": "Retail",
    "平均涨跌幅": -1.6354285714285715,
    "股票数量": 140
  },
  {
    "板块": "Aerospace & Defense",
    "平均涨跌幅": -1.6513333333333333,
    "股票数量": 60
  },
  {
    "板块": "Semiconductors",
    "平均涨跌幅": -1.7565591397849465,
    "股票数量": 93
  },
  {
    "板块": "Technology",
    "平均涨跌幅": -1.8212131147540984,
    "股票数量": 305
  },
  {
    "板块": "Hotels, Restaurants & Leisure",
    "平均涨跌幅": -2.0109345794392524,
    "股票数量": 107
  },
  {
    "板块": "Diversified Consumer Services",
    "平均涨跌幅": -2.1471428571428572,
    "股票数量": 49
  },
  {
    "板块": "Tobacco",
    "平均涨跌幅": -2.2216666666666667,
    "股票数量": 6
  },
  {
    "板块": "Leisure Products",
    "平均涨跌幅": -2.2888888888888888,
    "股票数量": 27
  },
  {
    "板块": "Industrial Conglomerates",
    "平均涨跌幅": -2.3875,
    "股票数量": 4
  },
  {
    "板块": "Financial Services",
    "平均涨跌幅": -2.4402651515151517,
    "股票数量": 264
  },
  {
    "板块": "Auto Components",
    "平均涨跌幅": -2.4438235294117647,
    "股票数量": 34
  },
  {
    "板块": "Transportation Infrastructure",
    "平均涨跌幅": -2.7466666666666666,
    "股票数量": 3
  },
  {
    "板块": "Electrical Equipment",
    "平均涨跌幅": -2.862611111111111,
    "股票数量": 180
  },
  {
    "板块": "Banking",
    "平均涨跌幅": -3.5647058823529414,
    "股票数量": 272
  },
  {
    "板块": "Automobiles",
    "平均涨跌幅": -3.5991304347826087,
    "股票数量": 23
  },
  {
    "板块": "Airlines",
    "平均涨跌幅": -5.002777777777777,
    "股票数量": 18
  }
]