[
  {
    "板块": "Automobiles",
    "平均涨跌幅": 4.22409090909091,
    "股票数量": 22
  },
  {
    "板块": "Energy",
    "平均涨跌幅": 1.9359668508287293,
    "股票数量": 181
  },
  {
    "板块": "Professional Services",
    "平均涨跌幅": 1.789294117647059,
    "股票数量": 85
  },
  {
    "板块": "Transportation Infrastructure",
    "平均涨跌幅": 1.5999999999999999,
    "股票数量": 3
  },
  {
    "板块": "Semiconductors",
    "平均涨跌幅": 0.8197938144329896,
    "股票数量": 97
  },
  {
    "板块": "Communications",
    "平均涨跌幅": 0.42871794871794877,
    "股票数量": 39
  },
  {
    "板块": "Chemicals",
    "平均涨跌幅": 0.4038571428571429,
    "股票数量": 70
  },
  {
    "板块": "N/A",
    "平均涨跌幅": 0.04620481927710842,
    "股票数量": 166
  },
  {
    "板块": "Machinery",
    "平均涨跌幅": -0.053963963963964016,
    "股票数量": 111
  },
  {
    "板块": "Logistics & Transportation",
    "平均涨跌幅": -0.30647058823529394,
    "股票数量": 17
  },
  {
    "板块": "Electrical Equipment",
    "平均涨跌幅": -0.34708791208791206,
    "股票数量": 182
  },
  {
    "板块": "Diversified Consumer Services",
    "平均涨跌幅": -0.3989795918367347,
    "股票数量": 49
  },
  {
    "板块": "Insurance",
    "平均涨跌幅": -0.48038834951456316,
    "股票数量": 103
  },
  {
    "板块": "Construction",
    "平均涨跌幅": -0.6914545454545454,
    "股票数量": 55
  },
  {
    "板块": "Food Products",
    "平均涨跌幅": -0.8615277777777778,
    "股票数量": 72
  },
  {
    "板块": "Industrial Conglomerates",
    "平均涨跌幅": -0.8625,
    "股票数量": 4
  },
  {
    "板块": "Road & Rail",
    "平均涨跌幅": -0.9011111111111111,
    "股票数量": 36
  },
  {
    "板块": "Technology",
    "平均涨跌幅": -0.9670967741935484,
    "股票数量": 310
  },
  {
    "板块": "Consumer products",
    "平均涨跌幅": -1.133578947368421,
    "股票数量": 95
  },
  {
    "板块": "Commercial Services & Supplies",
    "平均涨跌幅": -1.1672058823529412,
    "股票数量": 68
  },
  {
    "板块": "Media",
    "平均涨跌幅": -1.1690860215053762,
    "股票数量": 186
  },
  {
    "板块": "Telecommunication",
    "平均涨跌幅": -1.1975675675675677,
    "股票数量": 37
  },
  {
    "板块": "Building",
    "平均涨跌幅": -1.2921212121212122,
    "股票数量": 33
  },
  {
    "板块": "Life Sciences Tools & Services",
    "平均涨跌幅": -1.383076923076923,
    "股票数量": 52
  },
  {
    "板块": "Textiles, Apparel & Luxury Goods",
    "平均涨跌幅": -1.4075,
    "股票数量": 44
  },
  {
    "板块": "Banking",
    "平均涨跌幅": -1.4179087452471484,
    "股票数量": 263
  },
  {
    "板块": "Trading Companies & Distributors",
    "平均涨跌幅": -1.4633333333333334,
    "股票数量": 36
  },
  {
    "板块": "Financial Services",
    "平均涨跌幅": -1.5255639097744362,
    "股票数量": 266
  },
  {
    "板块": "Utilities",
    "平均涨跌幅": -1.608970588235294,
    "股票数量": 68
  },
  {
    "板块": "Auto Components",
    "平均涨跌幅": -1.7664705882352942,
    "股票数量": 34
  },
  {
    "板块": "Leisure Products",
    "平均涨跌幅": -1.7748148148148148,
    "股票数量": 27
  },
  {
    "板块": "Real Estate",
    "平均涨跌幅": -1.7881034482758622,
    "股票数量": 58
  },
  {
    "板块": "Retail",
    "平均涨跌幅": -1.852340425531915,
    "股票数量": 141
  },
  {
    "板块": "Hotels, Restaurants & Leisure",
    "平均涨跌幅": -1.9356363636363638,
    "股票数量": 110
  },
  {
    "板块": "Biotechnology",
    "平均涨跌幅": -2.0183736263736263,
    "股票数量": 455
  },
  {
    "板块": "Marine",
    "平均涨跌幅": -2.0296666666666665,
    "股票数量": 30
  },
  {
    "板块": "Packaging",
    "平均涨跌幅": -2.0310526315789477,
    "股票数量": 19
  },
  {
    "板块": "Pharmaceuticals",
    "平均涨跌幅": -2.136583850931677,
    "股票数量": 161
  },
  {
    "板块": "Health Care",
    "平均涨跌幅": -2.2104697986577184,
    "股票数量": 298
  },
  {
    "板块": "Distributors",
    "平均涨跌幅": -2.520952380952381,
    "股票数量": 21
  },
  {
    "板块": "Aerospace & Defense",
    "平均涨跌幅": -2.5768181818181817,
    "股票数量": 66
  },
  {
    "板块": "Airlines",
    "平均涨跌幅": -2.7600000000000002,
    "股票数量": 17
  },
  {
    "板块": "Beverages",
    "平均涨跌幅": -2.8663157894736844,
    "股票数量": 19
  },
  {
    "板块": "Metals & Mining",
    "平均涨跌幅": -3.102763157894737,
    "股票数量": 76
  },
  {
    "板块": "Tobacco",
    "平均涨跌幅": -4.145,
    "股票数量": 6
  },
  {
    "板块": "Paper & Forest",
    "平均涨跌幅": -4.634,
    "股票数量": 5
  }
]